anton_test.py
anton_test-2.0.0.dist-info/WHEEL
anton_test-2.0.0.dist-info/METADATA
anton_test-2.0.0.dist-info/RECORD
